omero_bifrost/__init__.py
omero_bifrost/cli.py
omero_bifrost/pull/__init__.py
omero_bifrost/pull/pull_ops.py
omero_bifrost/push/__init__.py
omero_bifrost/push/push_ops.py
omero_bifrost/query/__init__.py
omero_bifrost/query/query_ops.py
omero_bifrost/utils/__init__.py
omero_bifrost/utils/util_ops.py
omero_bifrost-0.0.5.dist-info/LICENSE
omero_bifrost-0.0.5.dist-info/METADATA
omero_bifrost-0.0.5.dist-info/WHEEL
omero_bifrost-0.0.5.dist-info/entry_points.txt
omero_bifrost-0.0.5.dist-info/top_level.txt
omero_bifrost-0.0.5.dist-info/RECORD
