Metadata-Version: 2.1
Name: omero-bifrost
Version: 0.0.5
Summary: Bifrost bridge for simplified large-scale transfer of bioimage data using an OMERO server
Home-page: https://github.com/luiskuhn/omero-bifrost
Author: Luis Kuhn Cuellar
Author-email: luis.kuhn@gmail.com
License: MIT
Classifier: License :: OSI Approved :: MIT License
Classifier: Operating System :: OS Independent
Classifier: Programming Language :: Python :: 3
Requires-Python: >=3.8
License-File: LICENSE
Requires-Dist: typer ==0.9.0
Requires-Dist: rich ==13.5.2
Requires-Dist: zeroc-ice ==3.6.5
Requires-Dist: omero-py ==5.13.1
Requires-Dist: omero-upload ==0.4.0
Requires-Dist: ezomero ==2.1.0
